{
  "title": "灣仔濕市場隱藏攻略：商務區裡的日常煙火與地道食材採買",
  "slug": "hongkong-shopping-wet-markets-wan-chai-灣仔濕市場隱藏攻略-商務區裡的日常煙火與地道食材採買-812a0f",
  "industry": "shopping",
  "category": "wet-markets",
  "area": "wan-chai",
  "url": "https://hongkong-encyclopedia.vercel.app/articles/hongkong-shopping-wet-markets-wan-chai-灣仔濕市場隱藏攻略-商務區裡的日常煙火與地道食材採買-812a0f.html",
  "published": "2026-07-14",
  "quality_score": 7.5,
  "word_count": 1945,
  "tags": [
    "灣仔濕市場",
    "香港街市",
    "灣仔美食",
    "灣仔購物",
    "香港自由行"
  ],
  "content": "灣仔給多數旅客的印象，是蘭桂坊的霓虹夜晚、是會展中心的博覽盛事、是穿梭於寫字樓之間的白領一族。然而，在這片金融與商業的高度競爭地帶，卻隱藏著香港最接地氣的市井生活場景——濕市場。與其專程前往傳統街市區，住在灣仔或因商務前來的旅客，其實可以在會議與購物之間，偷得浮生半日閒，直接在這個核心商業區體驗最真實的香港街頭煙火氣。\n\n灣仔的濕市場生態與其他傳統街市區截然不同。這裡的市場不以規模取勝，而是以「隱藏版」形態散落於商廈夾縫之間。旅客往往需要穿過一段短短的巷弄，才能發現原來在LV旗艦店對面的街角，竟有一檔經營了三十年的老字號魚丸檔；又或者在五星級酒店後方，藏著一間只做本地人生意的豆品作坊。這種「都市奇觀」式的反差，正是灣仔濕市場的最大特色——繁華與傳統僅一路之隔，現代消費與人情味共冶一爐。\n\n\n\n**推薦地點**\n\n灣仔街市（莊士敦道街市）可說是灣仔區內最核心的濕市場。這座三層高的市政大樓位於莊士敦道與灣仔道交界處，歷史可追溯至一九五零年代。地下層以海鮮及肉類檔口為主，每日清晨六時便有來自香港仔及筲箕灣的漁船直送到貨，鮮活海產的選擇不比傳統漁港遜色；二樓主要售賣蔬果，香港新界有機農場的產品在此設有專櫃，價格略高於一般攤位但品質有保證；三樓則是熟食中心「街市食坊」，海南雞飯、雲吞麵、港式奶茶等經典茶餐廳美食一應俱全，午餐時段常見西裝筆挺的白領與街坊鄰居同桌用膳，場面有趣。街市內多數檔口已接受八達通及電子支付，旅客毋需準備大量現金。\n\n位於灣仔與銅鑼灣交界的鵝頸街市，是另一個值得探索的去處。這個位於堅拿道東附近的市政街市雖然規模較小，但勝在人流相對稀疏，旅客可以更從容地與檔主交流。推薦關注地下層的海鮮檔口，經常有進口海產如加拿大龍蝦、日本帆立貝等，價格比一般凍肉店實惠約兩成，是旅客自行採購海鮮食材的好地方。街市旁邊的行人天橋底設有臨時攤檔區，下午時段會有流動水果檔在此擺賣，熱帶水果如芒果、榴槤價格相當具競爭力。\n\n如果時間允許，從灣仔港鐵站往北走約十五分鐘，即可抵達北角區的春秧街街市。這裡被譽為「最懷舊的香港街市」之一，保留了戰前唐樓群與露天市集並存的景觀。街道兩旁的攤檔售賣各類傳統食材，從潮汕滷味到客家梅菜一應俱全。春秧街的最大亮點是「一體化購物體驗」——整條街囊括生鮮食材、乾貨配料、街頭小食，旅客可以一次性採購齊備，再步行至附近的電車路總站，乘坐百年曆史電車返回灣仔，別有一番中西交融的港味。\n\n對於希望購買香港特產的旅客，灣仔道與太原街交界處的「明記海味」是個不可錯過的選擇。這家老店專營鮑參翅肚等海味乾貨，家族經營超過半世紀，老闆對食材等級如數家珍。店內提供散裝購買服務，旅客可以按需選購少量花膠、乾貝作為伴手禮，價格比機場免稅店實惠約三至四成。店內亦售賣即食港式湯包，配合街市購買的新鮮食材，回到酒店自行烹調，即可享受一頓簡易的港式煲湯體驗。\n\n最後推薦的是位於皇后大道東的「成記蔬果」。這家小型蔬果店的特色在於「產地直供」模式，老闆每日凌晨親自到新界農場取貨，確保蔬果的新鮮度。店內設有小型冷藏櫃，售賣預包裝的有機蔬菜組合，適合旅客購買後放入酒店冰箱儲存。價格方面，本地時令蔬果每斤約HK$15-30有機產品則在HK$40-60之間，略高於一般街市但品質穩定。\n\n\n\n**實用資訊**\n\n灣仔街市的營業時間為每日早上六時至晚上八時，熟食中心則至晚上九時。鵝頸街市開放時間為早上七時至下午六時。春秧街街市的露天攤檔主要集中在上午，午後人流漸減。交通方面，灣仔港鐵站A出口步行約五分鐘即可抵達莊士敦道街市；從灣仔會展新翼前往街市約需十分鐘路程，沿途會經過多間老字號茶餐廳，可一併探索。\n\n費用方面，灣仔區濕市場的食材價格與香港其他地區相若。海鮮每斤約HK$60-200，視乎品種及季節；豬肉牛肉每斤約HK$50-80；時令蔬果每斤約HK$10-30。旅客在街市購買食材後如需加工，可考慮前往街市內的熟食中心，部分檔口提供代客烹調服務，收費約HK$20-30。\n\n\n\n**旅遊小提示**\n\n灣仔區的濕市場與傳統旅遊區最大的不同在於「在地感」。這裡的檔主多數以廣東話為主要溝通語言，旅客可以嘗試以簡單英語或國語溝通，多數年輕檔主都能應對。若希望獲得更佳的購物體驗，建議避開上午十一時至下午一時的午市高峰期，選擇傍晚時段前往，不僅人流較少，部分檔口還會開始打折促銷當日剩餘食材。\n\n值得留意的是，灣仔作為商業區，週末部分街市檔口的營業時間會縮短或休息，建議旅客安排平日到訪。整體而言，灣仔濕市場的價值不在於規模，而在於其「隱匿於繁華」的獨特體驗——在最短的時間內，既能完成商務行程，又能深入當地人的日常生活，這種高效且接地氣的旅遊體驗，正是灣仔區的最大魅力所在。",
  "license": "CC BY 4.0"
}