{
  "title": "大嶼山宗教文化遺產：山海之間的信仰生活",
  "slug": "hongkong-tourism-cultural-heritage-lantau-大嶼山宗教文化遺產-山海之間的信仰生活-16bcfb",
  "industry": "tourism",
  "category": "cultural-heritage",
  "area": "lantau",
  "url": "https://hongkong-encyclopedia.vercel.app/articles/hongkong-tourism-cultural-heritage-lantau-大嶼山宗教文化遺產-山海之間的信仰生活-16bcfb.html",
  "published": "2026-03-24",
  "quality_score": 6.5,
  "word_count": 1507,
  "tags": [
    "大嶼山",
    "宗教文化",
    "文化遺產",
    "活態遺產",
    "寶蓮禪寺"
  ],
  "content": "說起香港的文化遺產，多數人可能先想到港島的老建築或新界的圍村，但其實大嶼山的宗教文化遺產同樣精彩。作為香港最大的島嶼，大嶼山不僅有天壇大佛和寶蓮禪寺這些知名地標，更藏著仍在運作的傳統佛寺、道觀和祠堂。這些宗教場所不是靜態的展示空間，而是居民日常生活的的一部分——這正是大嶼山文化遺產最迷人的地方。\n\n活態文化遺產的價值在於「正在發生」。寶蓮禪寺的師父們仍每日晨鐘暮鼓，天壇大佛前的祈福儀式吸引絡繹不絕的信眾，而東湧一帶的祠堂仍是村民祭祖聯誼的場所。走進這些地方，你能感受到的不是博物館般的距離感，而是信仰在當代社會中持續跳動的生命力。這種「活著的文化」，正是大嶼山與其他已開發為旅遊區的文化遺產最大的不同。\n\n說到大嶼山的宗教地標，天壇大佛肯定是最具代表性的。這尊戶外青銅佛像高34米，坐立於木魚峰上，俯瞰大嶼山海岸線。大佛於1993年落成，造價高達6,000萬港元，至今仍是全球最大的戶外青銅坐佛。參觀大佛免費，但若想進入大佛內部的蓮花座參觀（內有佛陀舍利），則需支付HK$20。值得注意的是，大佛在不同光線下呈現多樣風貌——晨光中莊嚴肅穆，夕陽下則顯得溫暖慈悲，想要拍出理想照片的話，建議預留充足時間。\n\n與天壇大佛相鄰的寶蓮禪寺，則是大嶼山歷史最悠久的佛教道場。寺廟建於1906年，最初名為「寶蓮庵」，後改為「寶蓮禪寺」，是香港佛教四大叢林之一。寺內建築融合了中式園林與南傳佛教風格，最著名的是供有四面佛的四面堂，以及可容納數百人的大雄寶殿。寶蓮禪寺的素齋在本地頗有名氣，位於寺院入口處的齋堂提供簡單的素食套餐，約HK$40-60即可享用一碗熱騰騰的羅漢齋麵，對登山後的旅人而言是難得的comfort food。\n\n想看更不一樣的宗教遺產，位於昂坪的羅漢寺是個驚喜。這座小型佛寺建於1970年代，以羅漢巖和觀音洞聞名。寺內有十八尊形態各異的羅漢石像，環境清幽，遊客遠比寶蓮禪寺少。羅漢寺不收門票，但寺外有個小型茶座，提供涼茶和桂花糕等傳統小吃，價格在HK$15-30之間。這裡適合想遠離人潮、靜心感受宗教氛圍的旅人。\n\n如果對道教文化感興趣，大嶼山的祠堂村值得一訪。東湧一帶保留了多座傳統祠堂，最著名的是已有超過200年歷史的劉氏家祠。祠堂建築融合了嶺南與客家風格，現在仍作為村民婚嫁祭祀的場所。每年農曆新年期間，祠堂前會舉行團拜活動，外嫁的族人會回鄉團聚，這種「活態」的宗族文化在其他地方已不多見。東湧古炮臺就在祠堂附近，這座建於1832年的花崗石炮臺是鴉片戰爭時期的海防設施，當年曾擊退英軍登陸，現在是香港法定古蹟。炮臺免費開放，但交通不太便利，建議乘計程車前往。\n\n最後不能不提大澳。這個被稱為「香港威尼斯」的漁村，除了棚屋和水上風光，還有傳統的神祇信仰。大澳天后宮建於清朝，至今已有超過150年歷史，每年農曆三月二十三的天后誕會舉行盛大巡遊，漁民會抬著天后神像出遊，場面熱鬧。這種結合了宗教與社群的傳統，正是活態文化遺產的最佳例證。\n\n前往大嶼山主要可乘昂坪360纜車或渡輪。昂坪纜車來回費用為HK$235（標準車廂）/ HK$350（水晶車廂），約25分鐘可達昂坪市集，再步行約10分鐘即可抵達天壇大佛和寶蓮禪寺。若從中環或屯門乘渡輪前往大澳，渡輪航程約50分鐘，單程約HK$40-50。巴士方面，由東湧市中心有多條巴士線可達昂坪和大澳，但班次較疏，建議查詢時刻表。\n\n\n旅遊小提示：宗教場所穿著宜樸素，避免穿背心短褲入寺。香港夏季悶熱多雨，戶外參觀需備防曬和雨具。大嶼山部分路段較陡峭，建議穿舒適步行鞋。若想體驗真正的宗教活動，可查詢農曆特定節慶的祭祀時間，那時參與者眾，更能感受在地信仰的活力。",
  "license": "CC BY 4.0"
}