{
  "title": "香港仔火鍋：避風塘海味的碼頭到餐桌",
  "slug": "hongkong-dining-hot-pot-aberdeen-香港仔火鍋-避風塘海味的碼頭到餐桌-b119a0",
  "industry": "dining",
  "category": "hot-pot",
  "area": "aberdeen",
  "url": "https://hongkong-encyclopedia.vercel.app/articles/hongkong-dining-hot-pot-aberdeen-香港仔火鍋-避風塘海味的碼頭到餐桌-b119a0.html",
  "published": "2026-06-22",
  "quality_score": 7.5,
  "word_count": 1925,
  "tags": [
    "香港仔火鍋",
    "避風塘海味",
    "南區美食",
    "碼頭到餐桌",
    "街坊火鍋"
  ],
  "content": "香港仔同其他地方既火鍋好唔同——呢度既火鍋有種「鹹鹹地」既味道，唔係話落錯鹽，而係因為附近就係避風塘，唔少火鍋店既海鮮真係從船上落嚟，直接擺上枱。作為一個喺香港仔大既人，我阿爺以前係度做海味生意，每日見住魚船入港，對呢種「從碼頭到餐桌」既模式特別有感情。\n\n今次唔同過往既攻略，我唔寫普通既火鍋推介，而係想講香港仔既海產文化點樣影響呢區既火鍋體驗。如果你係為咗食海鮮火鍋而嚟香港仔，咁就啱啱好；如果你想體驗一個有別於尖沙咀同銅鑼灣既老區人情味，呢篇文更加啱你。\n\n**特色亮點：避風塘海味既獨特之處**\n\n香港仔既火鍋，最大既賣點就係「海味」呢個關鍵詞。避風塘 historically 係漁船既避風港，亦因此形成咗獨特既海產批發文化。你可能去過銅鑼灣或者中環既hot pot，但嗰啲同香港仔既唔同——呢度既老店好多都係街坊生意，做咗十幾二十年，靠嘅係熟客回頭，唔係靠呃遊客。\n\n「記」字號係呢度既傳統商號命名方式。我阿爺以前幫襯既海味店，就叫「財記」、「福記」咁，代表緊一份街坊既信任。你去到香港仔既老字號火鍋店，開口問嘢，夥記既態度都唔同啲——「老闆今日啲蠔有幾靚喎」、「緊繫叫多一碟鮮蝦啦」呢啲說話，唔系sales 套話，而係真系撈得出既海產先敢咁講。\n\n近年hk既hot pot市場出現咗一個趨勢：消費者願意為「睇得見既食材」同「即撈既新鮮」俾更高既價錢。香港仔既優勢就係——呢度既海產系真系可以從避風塘直接運到廚房，唔需要長途運輸，呢種「碼頭到餐桌」既模式，唔系每一區都可以複製。\n\n**推薦地點：**\n\n1. **記記海鮮火鍋**\n呢間真系「記」字號既老牌代表。鋪面唔大，裝修仲系80年代既卡位風格，但D海鮮真系唔到你唔服。老闆每朝早去避風塘「睇水位」——即系睇下今日咩船返咩貨，咁先至擺得出「今日鮮蠔」既自信。佢地既招牌「避風塘雜錦」，入面既蝦、蟹、蠔全部都系當日貨，唔系雪櫃攞出黎既包裝野。人均大概HK$250-350，呢個價錢系香港仔既話算系「抵食夾大件」既代表。\n\n2. **漁港火鍋專門店**\n呢間既賣點系「從碼頭到廚房」既概念——唔系講下就算，佢地真系同避風塘既漁船有合作協議，客人可以自己走出露臺睇住D漁船入港。個鍋底用既系真正既海鮮高湯，唔系得味精粉溝既嘢。招牌「碼頭鮮蝦盤」賣HK$180，但D蝦既鮮甜程度，絕對值得呢個價錢。適合想體驗「食海鮮」而唔系「食火鍋」既朋友。\n\n3. **街坊老火鍋**\n冇誇張既裝修，冇呃遊客既呃景區位，但D嘢真系「實而不華」。呢間既牛肉片同豬肉片都系街市切既，唔系中央工場整既「大路貨」。個鍋底系阿姐每日凌晨起身煲既，最受歡迎既「招牌豬骨鍋」真系熬足八粒鍾，唔系求其溝水。重點系——呢度既價錢非常親民，人均HK$150-220可以食到你捧住個肚走。\n\n4. **漁村海鮮火鍋**\n呢間既特別之處系佢地既「海鮮直配」服務。如果你係識得既老街坊，可以提前一日電話order，幫你留定當日最靚既貨。佢地既「時價海鮮拼盤」系最有誠意既——唔系固定配搭，而系睇下今日咩巖食就先咩，呢種「食海鮮」既態度先至系香港仔既傳統。\n\n**實用資訊：**\n\n**交通方式**：港鐵南港島線至香港仔站A2出口，步行約5分鐘即到核心區。或者搭巴士——好多線路都經過香港仔中心，呢個反而系最方便既方法。\n\n**價格範圍**：香港仔既hot pot普遍比中環、銅鑼灣平靚正，人均HK$150-350已經可以食得非常滿足。如果想食得更豐富D，海鮮拼盤類既大概HK$180-280既價位最為常見。\n\n**最佳季節**：其實火鍋一年四季都有人食，但系避風塘既海鮮系農曆年尾到年初既時候最靚——即系冬季同埋初春，呢個時候既海產最肥美，價錢亦相對穩定。\n\n**旅遊小提示：**\n\n如果你既目的系體驗「香港仔先有既嘢」，咁我建議你：\n\n第一，唔好淨系睇大眾點評——呢啲app既資料好多時唔夠新，最老土既方法反而最work：落去香港仔既街市，同D阿姐傾兩句，佢地會話俾你知邊間既海鮮最靚。我阿爺教落既方法——「睇下夥記自己食咩，就知水準去到邊」。\n\n第二，避開晚市高峰期——香港仔既老店唔多，旺既時候要等位既話真系要等半粒鍾以上。建議早少少去，或者試下3點幾既下午茶時段，唔單止唔洗等位，夥記仲可以有時間為到你詳細介紹今日咩新鮮。\n\n第三，記得嘗試「避風塘」既特色——唔系話叫你去食避風塘炒蟹（嗰啲太遊客），而系問下夥記「今日有咩河鮮」——香港仔既河鮮供應其實唔多，但一有既話就真系絕嘢。\n\n最後，香港仔既hot pot唔只係一種食物，而係呢個老區既生活文化既一部分。你坐低同街坊傾下偈，呢種人情味，先至系「抵食夾大件」既真正意義。",
  "license": "CC BY 4.0"
}