{
  "title": "中環節慶盛會：繁華都市的文化創意祭典",
  "slug": "hongkong-entertainment-festivals-central-中環節慶盛會-繁華都市的文化創意祭典-204821",
  "industry": "entertainment",
  "category": "festivals",
  "area": "central",
  "url": "https://hongkong-encyclopedia.vercel.app/articles/hongkong-entertainment-festivals-central-中環節慶盛會-繁華都市的文化創意祭典-204821.html",
  "published": "2026-06-01",
  "quality_score": 6.5,
  "word_count": 1783,
  "tags": [
    "中環節慶",
    "香港節日",
    "文化藝術",
    "創意產業",
    "節慶活動"
  ],
  "content": "說到中環的節慶活動，很多人第一時間想到的是聖誕節期間那些金碧輝煌的巨型聖誕樹和各國領事館舉辦的慶祝派對。沒錯，作為香港的核心商業區，中環的節慶活動確實充滿濃厚的國際氛圍，但如果只看到這些，就太可惜了。近年來，中環的節慶活動正在發生微妙的轉變——傳統文化慶典與創意產業展覽開始佔據越來越重要的位置，這種融合正是讓中環節慶與眾不同的獨特魅力。\n\n中環節慶的最大特色在於「跨界混搭」。這裡不像銅鑼灣那樣以大型購物優惠為主打，也不像灣仔保留那麼多傳統市井氣息，中環的節慶活動更像是一個文化創意平臺。每逢重大節日，中環的蘇豪區（SoHo）和荷李活道一帶就會出現各種 Pop-up 設計展覽、露天藝術裝置，以及結合餐飲體驗的主題活動。這種將商務區功能與創意產業結合的模式，讓中環的節慶呈現出既都會又文藝的雙重性格。\n\n更重要的是，中環作為香港藝術文化機構的集中地，節慶期間會舉辦許多與藝術展覽相結合的特別活動。香港海事博物館、香港文物探知館在節日期間常有特別企劃，而大館的露天廣場則會變身為街頭藝人和獨立音樂人的表演舞臺。這種，將歷史建築與現代慶典結合的做法，讓參加者在感受節日氣氛的同時，也能近距離接觸香港的文化藝術。\n\n說了那麼多，讓我推薦幾個中環節慶期間最值得造訪的地點：\n\n第一個推薦是大館（Tai Kwun）。這裡原本是前中央警署建築群活化而成，現在是香港最具代表性的文化藝術空間之一。大館的節慶活動特別之處在於會將歷史建築本身作為展覽的一部分聖誕期間，大館的露天廣場會搭建融入建築特色的節日裝置，而非一般的商業聖誕樹。同時，大館內的各類 Gallery 會舉辦應節的限定展覽，通常票價在 HK$30-HK$150 之間，視展覽規模而定。開放時間一般是朝10晚10，節日期間可能會延長。建議下午前往，先參觀展覽，待到傍晚時欣賞夜景，最能感受歷史與現代交織的節日氛圍。\n\n第二個推薦是PMQ元創方。這裡是中環創意產業的核心地標，由前已婚警察宿舍活化改造而成。PMQ在節慶期間會搖身變成設計師們的 Showcase 平時藏在工作室裡的獨立設計品牌會在此設攤，售賣自家設計的節日手工飾品和創意禮物。這裡的節慶活動相對小眾，但正因如此，能找到市面上買不到的獨特設計。PMQ的節日市集通常免費入場，個別工作坊課程可能收費約 HK$200-HK$500，建議提前在官方網站查詢預約。注意這裡週一休息，不要白跑一趟。\n\n第三個推薦是中環海濱長廊。這裡是近年香港節慶活動的新熱點，空間寬敞且面向維多利亞港，是觀看煙火表演的最佳位置之一。每逢國慶、農曆新年等重大節日，政府都會在此舉辦免費的煙火匯演。建議提早兩小時到場霸位，屆時人潮非常可觀。海濱長廊的優勢在於完全免費，而且是戶外空間，空氣流通，對親子家庭特別友善。毗鄰的中環渡輪碼頭在節日期間也會裝飾得別有風味，值得順道一看。\n\n第四個推薦是蘇豪區（SoHo）的高階餐飲體驗。雖然這裡不是傳統意義上的「節慶活動」，但中環的蘇豪區在節日期間會出現各種節日限定選單和主題派對。蘭桂坊一帶的酒吧餐廳會推出聖誕特調、新年套餐等，消費屬於中上檔次，平均消費約 HK$300-HK$800 一人。適合想過一個較為精緻的節日夜晚的讀者。需要提醒的是，節日期間蘭桂坊一帶人潮擁擠，且酒精消費較高，建議結伴同行並注意安全。\n\n最後一個推薦可能比較少人注意到——中環街市的活化空間。位於中環市政大廈內的街市在節日期間有時候會舉辦小型的主題市集，售賣手工藝品和節日食品。這裡的優勢是完全免費，而且能感受到local的生活氣息，與商場的人工地毯聖誕裝飾形成有趣對比。開放時間通常是上午6時至午夜12時，市集活動多在下午至晚間。\n\n實用資訊方面，前往中環首選港鐵 MTR，港島線或荃灣線均可直達，出閘後步行約5分鐘即可到達各個推薦地點。如從羅湖或落馬洲口岸入境，建議使用八達通支付車資。節日期間中環交通可能擁塞，建議避開放上下班高峰期。\n\n最後給幾點小提示：中環的節慶活動雖然集中在節日期間，但其實每個季度的主題都不同，春節有新春花展、春季有藝術節、夏季有啤酒節、冬季則是聖誕新年檔期。如果時間允許，避開聖誕除夕等極高峰日，人潮相對較少，體驗會更好。再提醒一次，大館和 PMQ 這類文創空間的節日活動通常需要提前在網上預約，當天現場候補名額有限，切勿摸黑前往。",
  "license": "CC BY 4.0"
}