{
  "title": "中環隱藏節慶：本地人帶路的社群慶典體驗",
  "slug": "hongkong-entertainment-festivals-central-中環隱藏節慶-本地人帶路的社群慶典體驗-64edd2",
  "industry": "entertainment",
  "category": "festivals",
  "area": "central",
  "url": "https://hongkong-encyclopedia.vercel.app/articles/hongkong-entertainment-festivals-central-中環隱藏節慶-本地人帶路的社群慶典體驗-64edd2.html",
  "published": "2026-05-23",
  "quality_score": 6.5,
  "word_count": 976,
  "tags": [
    "中環節慶",
    "本地體驗",
    "社區活動",
    "香港文化",
    "隱藏景點"
  ],
  "content": "說起中環的節慶，很多人第一反應是蘭桂坊的派對或大型藝術博覽會。但若你願意走進巷弄深處，會發現這裡還藏著另一種節慶風景——街坊鄰裡之間流傳多年的社群慶典。這些活動規模不大，卻承載著濃厚的本土記憶，也是體驗香港真實節慶文化的好選擇。\n\n中環既然是全港最早發展的市區之一，百年來累積了不少傳統習俗。荷李活道一帶仍保留著多間老店，每逢農曆新年和中秋，店鋪會自發舉辦小型慶祝活動，例如在中秋期間於街道上擺放手工花燈，讓附近的街坊和遊客一同欣賞。這類小型慶典沒有官方宣傳，通常只靠街坊口耳相傳，卻格外有氣氛。若幸運遇到，不妨加入人群，感受那份鄰裡之間的溫馨。\n\n除傳統節慶外，中環的社群中心也會舉辦各種免費文化活動。大館每月都會在週末安排導賞團和工作坊，有時會配合節慶主題推出限定節目，例如端午節的手作香囊班或重陽節的傳統工藝展。這類活動通常名額有限，建議提前在大館官網預約。此外，卑利街和些釐街一帶的街市在傳統節日前後會特別熱鬧，偶爾有本地藝術團體在此進行小型表演，為日常的購物環境增添節慶氣息。\n\n帶孩子旅行的家庭族，中環其實有適合小朋友參加的節慶活動。香港公園每逢聖誕和農曆新年都會設定親子裝置藝術，並舉辦小朋友手作坊。這裡的節慶佈置偏向溫馨家庭風格，而非熱鬧party路線，非常適合想避開人潮、輕鬆過節的家庭。香港摩天輪在節日期間也會推出應節主題，乘坐一次的費用約為HK$20，可俯瞰維多利亞港的節日全景，是浪漫又經濟的節慶體驗。\n\n若想感受不一樣的節慶氣氛，推薦前往中環海濱的臨時市集。這個空間在不同節日會搖身變成主題慶祝廣場，例如新春期間的年宵市場、農曆七月的中元節祈福儀式等。市集的氛圍介於傳統與創意之間，既有本地手作攤位，也有街頭表演，票價視具體活動而定，多數情況下免費入場。這類活動資訊通常釋出在社交媒體專頁，建議出發前搜尋「中環海濱活動」檢視最新訊息。\n\n另外提醒幾件事：中環的主要節慶活動通常集中在假期前後，人潮眾多，若想享受較寧靜的體驗，建議選擇平日上午或傍晚前往。部分巷弄狹窄，節日期間可能實施人流管制，屆時需配合警方安排。再者，香港節慶期間部分商店和餐廳營業時間會調整，出發前最好確認擬拜訪地點的開放時間，避免白跑一趟。最後，切勿誤會社群慶典為大型觀光活動，這些本質上是街坊之間的慶祝，保持安靜尊重、不要打擾居民生活才是遊客應有的態度。",
  "license": "CC BY 4.0"
}