{
  "title": "尖沙咀廟宇導覽：鬧市中的祈福靜土",
  "slug": "hongkong-tourism-temples-tsim-sha-tsui-尖沙咀廟宇導覽-鬧市中的祈福靜土-934a58",
  "industry": "tourism",
  "category": "temples",
  "area": "tsim-sha-tsui",
  "url": "https://hongkong-encyclopedia.vercel.app/articles/hongkong-tourism-temples-tsim-sha-tsui-尖沙咀廟宇導覽-鬧市中的祈福靜土-934a58.html",
  "published": "2026-07-17",
  "quality_score": 6.5,
  "word_count": 1795,
  "tags": [
    "尖沙咀廟宇",
    "香港宗教文化",
    "天后廟",
    "黃大仙祠",
    "九龍祈福"
  ],
  "content": "說起尖沙咀，多數人想到的是海港城、太空館和維多利亞港的璀璨夜景。但在這個香港最繁華的購物與旅遊區深處，藏著幾座歷史悠久的廟宇，為行色匆匆的都市人保留了一方寧靜的祈福空間。對於從澳門來的旅客而言，尖沙咀的廟宇特別值得一訪——這裡的廟宇規模雖不及澳門的媽閣廟或觀音堂，卻展現了香港在都市發展中保留傳統信仰空間的獨特模式。\n\n尖沙咀的廟宇群主要集中在尖沙咀東部的天后廟道一帶，與廣東道、梳士巴利道等主要街道保持適當距離，形成「鬧中取靜」的格局。這些廟宇大多建於20世紀初，當時尖沙咀仍是漁民聚集的沿海社群，天后廟正是為守護海上平安而建。如今周圍已被高樓大廈包圍，但廟宇本身和周邊的福德祠、土地公仍持續運作，展現出香港都市更新中宗教空間被保留下來的難得案例。\n\n**推薦地點**\n\n**尖沙咀天后廟**是這裡最具代表性的廟宇，規模雖不大，卻是尖沙咀歷史最悠久的宗教建築。廟宇供奉天后娘娘，據說建於1910年代末期，當時尖沙咀仍是一個小漁村。建築風格為傳統清代兩進式設計，屋脊上的石灣陶塑精細依然，內部保留了大量歷史文物。最難得的是，廟宇至今仍有本地居民前來參拜，每逢天后誕辰（農曆三月廿三），整條天后廟道都會擺滿賀誕的花牌和戲棚，熱鬧程度與澳門媽閣廟的誕期慶典相比毫不遜色。廟外的廣場設有香爐和祈福鐘，遊客可以體驗傳統的參拜流程。\n\n**黃大仙祠（九龍總堂）** 位於九龍塘窩打老道，雖然嚴格來說位於九龍塘而非尖沙咀核心區，但從尖沙咀MTR站出發僅兩站即可到達，是許多旅客會順道參訪的熱門廟宇。這裡是嗇色園在香港的本廟，供奉黃大仙師，以「有求必應」的靈驗聞名。與澳門的媽閣廟不同，黃大仙祠最大的特色是可以「求籤」——廟內設有專門的籤筒和解籤攤位，遊客只需港幣20元即可求籤問卜。籤文以繁體中文和簡體中文並列，也有英文譯本，方便不同背景的遊客。記得求籤後可以到廟外的解籤攤檔請師傅解惑，這裡的解籤費用大約每次港幣50-100元，豐儉由人。\n\n**福德祠與土地廟群**分散在尖沙咀東部的巷弄之間，是容易被忽略的「隱藏版」景點。在天后廟道和加連威老道交界處，有一座小小的福德祠，供奉土地公。別看廟宇迷你，香港人相信土地公是當地的守護神，生意人或附近的住戶逢年過節都會前來供奉。另一座位於漆鹹道南附近的土地廟則更為熱鬧，廟前常年擺放著居民供奉的水果和鮮花，反映出濃厚的社群信仰氛圍。這些小型廟宇雖然不具觀光規模，卻是觀察香港本地宗教生活的最佳視窗。\n\n**紅磡觀音廟**位於紅磡道，距離尖沙咀僅一站MTR車程，是九龍區最著名的觀音廟之一。廟宇建於清朝年間，擁有超過150年歷史，是香港法定古蹟。這裡的觀音像莊嚴肅穆，廟內空間寬敞，參拜時不會感到擁擠。最特別的是觀音廟設有「觀音借庫」的傳統習俗，類似澳門媽閣廟的「借庫」習俗，每年農曆正月廿六是觀音開庫的日子，吸引大批善信前來借取「庫銀」——其實是一種象徵性的借據，據說可以借來一年的好運和財運。借庫是完全免費的，但很多遊客會隨喜捐獻港幣10-20元。\n\n**實用資訊**\n\n**交通方式**：尖沙咀天后廟可搭乘MTR至尖沙咀站L1出口，沿麼地道步行約10分鐘即可到達。黃大仙祠可搭乘MTR至黃大仙站B2出口，步行約3分鐘。紅磡觀音廟可搭乘MTR至紅磡站A1出口，沿蕪湖街步行約5分鐘。所有地點都接受八達通支付交通費，非常方便。\n\n**費用**：大部分廟宇參觀免費，求籤約港幣20元，解籤約港幣50-100元，隨喜功德金額自定。\n\n**開放時間**：一般為早上7時至傍晚6時，部分廟宇如黃大仙祠開放至晚上9時。建議避開中午12時至下午2時的酷熱時段前往。\n\n**旅遊小提示**\n\n參拜時切記不要踩踏廟宇的門檻，這在華人傳統中被視為不敬。女性旅客應避免在生理期期間進入廟宇的核心拜祭區域，這是出於尊重傳統習俗的考量。如果想體驗完整的參拜流程，可於廟外的香燒店請購香燭，一般港幣10-20元已足夠。對於從澳門來的旅客，香港的廟宇文化與澳門有相似之處，但香港廟宇更強調「問卜」功能，且解籤服務更為普遍，這是值得一試的在地體驗。\n\n尖沙咀的廟宇或許不如澳門的媽閣廟歷史悠久，規模也不及內地名山大川的千年古剎，但正是這種「小而美」的都市信仰空間，讓人感受到香港這座城市在快速發展中仍保留的那份傳統溫度。走累了海港城的街區不妨拐進天后廟道，在裊裊香火中為旅程祈一份平安。",
  "license": "CC BY 4.0"
}