{
  "title": "尖沙咀維港遊：從海港閱讀香港城市天際線的建築密碼",
  "slug": "hongkong-tourism-harbour-cruise-tsim-sha-tsui-尖沙咀維港遊-從海港閱讀香港城市天際線的建築密碼-121bf9",
  "industry": "tourism",
  "category": "harbour-cruise",
  "area": "tsim-sha-tsui",
  "url": "https://hongkong-encyclopedia.vercel.app/articles/hongkong-tourism-harbour-cruise-tsim-sha-tsui-尖沙咀維港遊-從海港閱讀香港城市天際線的建築密碼-121bf9.html",
  "published": "2026-06-30",
  "quality_score": 6.5,
  "word_count": 1503,
  "tags": [
    "尖沙咀景點",
    "維港遊",
    "城市天際線",
    "攝影指南",
    "海濱漫步"
  ],
  "content": "說起維港遊，大多人首先想到的是從港島望向九龍的經典視角。但如果你反過來站上尖沙咀的碼頭，背靠著近四十年累積的摩天樓群，面向對岸港島的建築變遷，會發現一個完全不同的香港敘事。這不是單純的觀光，而是一堂live版的城市設計課。\n\n維多利亞港的兩岸，其實是兩種截然不同的城市性格。九龍側的尖沙咀，代表著香港對密度與效率的執著；港島側的中環與灣仔，則是金融實力與國際野心的象徵。站在尖沙咀海濱，你看到的每一棟大樓，都記錄著香港經濟起飛的某個瞬間。\n\n【亮點特色】\n\n尖沙咀維港遊的核心價值，在於「閱讀」而非「觀看」。白天陽光直射時，玻璃幕牆反射的是冷冽的商業氣息；傍晚五至六點的「藍調時刻」，天光與建築燈光形成層次，這是拍攝城市天際線的黃金時間。維港的夜景被《國家地理》列為世界三大夜景之一，但真正的精髓在於從尖沙咀望向港島時，那種「城市森林」層層疊疊的視覺深度。\n\n尖沙咀海濱全約兩公里，適合用「步行的速度」來閱讀。從天星碼頭到香港科學館，不同區段呈現不同的建築時代密碼。中間段（星光大道至太空館外）最適合初訪者；末端（紅磡海底隧道上方）則是當地人最推薦的私房景點，遊客少、角度更開闊。\n\n【推薦地點】\n\n\n1. 天星碼頭（Star Ferry Pier）\n地址：尖沙咀碼頭（近鐘樓）\n特色：天星小輪不只是交通工具，更是香港百年公共交通的活化石。選擇上層座位視野更佳，票價僅HK$2.5（週一至週六）/ HK$3.4（週日及假期），這個價格三十年來幾乎沒漲過。渡輪航程約七分鐘，是價效比最高的維港體驗。\n\n2. 星光大道（Avenue of Stars）\n地址：尖沙咀海濱\n特色：李小龍、梅艷芳、梅愛芳等107位巨星掌印一字排開，但最大亮點是望向對岸港島的無遮擋視線。傍晚五點後補光燈亮起，配合維港夜景，是拍攝天際線的經典角度。這裡的問題是週末人潮較多，建議平日下午前往。\n\n3. 麼地道尖沙咀東（East Tsim Sha Tsui）\n地址：麼地道海濱\n特色：相較於星光大道的人潮，這段更安靜、餐廳選擇更多。港鐵（MTR）尖東站N2/N3出口步行三分鐘即達。這裡的優勢是能同時看到港島天際線與香港島南面的山景，層次感更豐富。\n\n4. 太空館外觀景臺（Hong Kong Space Museum）\n地址：梳士巴利道10號\n特色：免費開放的戶外觀景臺，正對港島中環核心區。旁邊就是香港文化中心，看完維港夜景可以直接進去看展或聽音樂會。這裡的視角比星光大道更遠，適合使用長焦鏡頭拍攝建築特寫。\n\n5. 紅磡碼頭（Hung Hom Pier）\n地址：紅磡繞道\n特色：當地人的私房推薦。從紅磡站步行五分鐘，這裡沒有遊客團隊，只有散步的居民和晨運客。望向對面是香港會議展覽中心與金紫荊廣場，視角比中環更正面，適合欣賞建築群的整體輪廓。\n\n【實用資訊】\n\n交通：港鐵（MTR）尖沙咀站E出口即達星光大道；尖東站N2出口往麼地道方向。渡輪可選荃灣線或屯門線至中環/灣仔。\n\n費用：天星小輪單程HK$2.5-3.4；維多利亞港遊覽船（天星小輪以外）約HK$150-250，視船公司與時段而定。尖沙咀海濱全程免費。\n\n營業時間：維港海濱24小時開放；天星小輪約06:30-23:30（灣仔線）/ 06:30-00:20（中環線），班次密集，約10-15分鐘一班。\n\n【旅遊小提示】\n\n\n維港的光線變化有兩個最佳時段：傍晚五點至六點的「藍調時刻」最適合拍攝天際線剪影；晚上八點整的幻彩詠香江雷射光雕匯演（免費）則是夜景高潮。尖沙咀海濱全程平坦寬敞，適合輪椅使用者，但部分碼頭設施較舊，須注意潮濕地面。冬季海風較大，建議帶備薄外套。",
  "license": "CC BY 4.0"
}