{
  "title": "灣仔活態文化：巷弄間的傳承故事",
  "slug": "hongkong-tourism-cultural-heritage-wan-chai-灣仔活態文化-巷弄間的傳承故事-755242",
  "industry": "tourism",
  "category": "cultural-heritage",
  "area": "wan-chai",
  "url": "https://hongkong-encyclopedia.vercel.app/articles/hongkong-tourism-cultural-heritage-wan-chai-灣仔活態文化-巷弄間的傳承故事-755242.html",
  "published": "2026-06-30",
  "quality_score": 6.5,
  "word_count": 1354,
  "tags": [
    "灣仔文化遺產",
    "活態傳承",
    "傳統老店",
    "香港島歷史",
    "灣仔深度遊"
  ],
  "content": "灣仔給人的第一印象往往是熱鬧的酒吧區和會展中心，但走進莊士敦道與皇后大道東之間的巷弄，卻藏著香港最動人的生活文化。這裡的文化遺產不是靜態的歷史建築，而是持續運作了數十年的老店舖——師傅仍在手工製作，爐火仍舊燃燒，這些「活態遺產」才是灣仔最迷人的文化風景。\n\n走進大有街與蘭杜街一帶，會發現灣仔保留著香港島難得的傳統工業聚落。福德祠附近的「杜師傅太極拳會」是社群武術教育的據點，但更值一提的是巷弄中的傳統手作行業——這裡有仍在使用半世紀老機器的人工皮革店，也有堅持手工訂造的西裝裁縫。這些店舖不是為了觀光而儲存，而是因為真正有本地顧客支援，才能在高地價的灣仔核心區生存下來。\n\n**譚記竹昇麵**是灣仔活態文化的代表。位於莊士敦道近灣仔站出口位置的這家老店，每天清晨六點開始以傳統竹昇麵桿打製雲吞麵。師傅坐在粗大的竹竿上，利用體重反覆壓製麵糰，這種技法在香港已剩不到十家店仍在使用。招牌雲吞麵HK$38，鮮蝦雲吞粒粒飽滿，湯底用大地魚和羅漢果熬製，回甘清甜。店內只有六個座位，繁忙時段需要併桌，但這正是香港傳統雲吞麵店的日常風景。\n\n**永祥鐘錶行**位於菲林明道與軒尼詩道交界，是灣仔超過五十年歷史的本地鐘錶維修店。店內擺滿了指標、齒輪和微型螺絲，師傅黃伯伯從年輕時學師至今，維修過無數家庭的傳統機械錶。這裡不只修錶，更是社群情感的連繫點——很多街坊拿著父親留下來的手錶前來修理，順便聊聊天。維修費用根據問題複雜程度，通常在HK$80-300之間，透明合理。\n\n**和昌大押**位於莊士頓道與謝斐道之間，是香港島少數仍維持傳統外觀的當舖。樓高三層的騎樓式建築，綠色鐵閘和傳統招牌儲存完整，現在雖以貸款業務為主，但建築本身已列入二級歷史建築。站在門外可以拍到典型的戰前香港商舖外觀，是認識香港昔日商業建築的好教材。\n\n**慧惠婆豆腐花**隱藏在太原街與交加街之間的巷弄中，是灣仔老街坊才知道的糖水檔。由一對老夫婦經營超過四十年，每天以傳統石膏點漿製作豆腐花，口感嫩滑、豆香濃鬱。招牌腐竹糖水只賣HK$12，是灣仔區內最便宜的傳統糖水之一。這種在大型連鎖店衝擊下仍能生存的街檔，代表著香港草根飲食文化的韌性。\n\n**藍屋建築群**位於石水渠街，是香港少數保留完整戰前唐樓群的街區。整條街的建築外牆漆成藍色，包括藍屋、黃屋和橙屋，其中藍屋現為香港故事館，展示昔日居民的生活痕跡。這些唐樓現在仍有居民居住，是「活生生的社群」而非單純的博物館。免費參觀外部，內部展覽門票HK$20。\n\n**交通方面**，灣仔站MTR港島線及荃灣線直達，多條巴士和小巴線經過。從港澳碼頭過來可乘坐MTR東鐵線到金鐘轉港島線，一程直達。太原街一帶建議步行參觀，從灣仔站A3出口步行約五分鐘即可到達和昌大押一帶。\n\n**時間安排**建議預留半天。早上九點先到譚記吃早餐（營業時間07:00-14:00），之後步行參觀藍屋建築群（約30分鐘），中午在慧惠婆吃糖水，下午參觀永祥鐘錶行（建議14:00後前往，師傅通常下午較有空閒聊天）。\n\n灣仔的文化遺產不在於宏大的歷史敘事，而在於這些仍在運作的老店——它們用日常的堅持，儲存著香港最珍貴的生活技藝。來灣仔不要只去會展中心，走進巷弄裡，看看那些師傅的手、聽聽那些老店的聲音，才是真正的文化體驗。",
  "license": "CC BY 4.0"
}