{
  "title": "旺角夜生活：年輕人的遊樂場與24小時不夜城生態",
  "slug": "hongkong-entertainment-nightlife-mong-kok-旺角夜生活-年輕人的遊樂場與24小時不夜城生態-26f1b1",
  "industry": "entertainment",
  "category": "nightlife",
  "area": "mong-kok",
  "url": "https://hongkong-encyclopedia.vercel.app/articles/hongkong-entertainment-nightlife-mong-kok-旺角夜生活-年輕人的遊樂場與24小時不夜城生態-26f1b1.html",
  "published": "2026-03-24",
  "quality_score": 6.5,
  "word_count": 1769,
  "tags": [
    "旺角夜生活",
    "香港娛樂",
    "遊戲機中心",
    "卡拉OK",
    "二次元文化"
  ],
  "content": "旺角的夜生活長期被美食街和購物商圈的光環所掩蓋，但真正深夜11點以後走入朗豪坊和新世紀廣場，你會發現這裡是香港年輕人最瘋狂的娛樂陣地。這不是酒吧街，也不是傳統夜市，而是以遊戲機中心、卡拉OK、動漫店鋪為核心的亞文化社交生態。週末深夜，服務業上班族、設計師、遊戲玩家和宅文化愛好者聚集於此，形成了一股獨有的青年夜間能量。\n\n**遊戲機中心：深夜的社交通道**\n旺角號稱「遊戲機中心最密集的區域」。光是朗豪坊周邊就有4-5家專業遊戲機大廳，從節奏遊戲、格鬥遊戲到抓娃娃機應有盡有。與其說是遊樂場，不如說是年輕人的社交通道。同事下班後相約來打幾局節奏遊戲，或一群朋友排隊挑戰格鬥遊戲對戰，這已是旺角上班族的常規放鬆儀式。特別是週五晚上11點到凌晨1點，遊戲機中心人流達到高峰，男女玩家比例相當，打破了傳統「電玩宅男」的刻板印象。\n\n2026年中國遊戲版號發放加速推動了亞洲遊戲生態快速整合，這也直接刺激香港遊戲機中心的硬體更新。你會明顯感受到今年新進的遊戲機型號增加，經營者在硬體投資更積極，遊戲種類的更新週期也在縮短。不少連鎖遊戲廳甚至開始引進最新的街機版本和獨家機種，變成了一場硬體競速賽。\n\n**卡拉OK：從下班儀式到深夜狂歡**\n旺角的卡拉OK文化分為兩個世界。連鎖品牌（Neway、Partyroom等）佔據主流市場，提供標準包廂體驗，價格HK$100-200/小時，是服務業員工和上班族的首選。但更有趣的是「小店卡拉OK」的生態——位於朗豪坊、新世紀廣場後街的小型自助卡拉OK，只有3-5間包廂，卻往往比連鎖店更受年輕人歡迎。\n\n為什麼？小店的歌曲庫更新快得多，店員會主動加入日本、韓國的新發行歌曲，連鎖大店的更新速度往往跟不上。價格也更便宜，通常HK$60-120/小時，接受1-2人散客，非常適合一個人消遣或臨時相約。對於外地遊客，建議直接進朗豪坊往樓梯間走，會發現一整條「卡拉OK小店街」，密度之高在香港其他地區很難找到。\n\n**動漫/二次元文化的聚集地**\n旺角與其他夜生活區域最大的差異在於動漫和二次元文化的滲透。這裡有專門賣動畫周邊、公仔、遊戲手辦的店鋪，有日式雜貨小店，有動漫主題咖啡館。晚上10點進入西洋菜南街或朗豪坊，會看到年輕人三三五五地進出小店，有人提著剛買的手辦袋，有人在店內試玩新上市的遊戲周邊。\n\n相比灣仔和銅鑼灣的快餐式消費文化，旺角的夜間消費有更多「逗留和社交」的成分。人們不是匆匆趕場，而是願意在一家店裡坐30分鐘，和同好交流最近的新番、遊戲發售或周邊話題。這個生態並不排外，反而相當包容——無論你是資深愛好者還是初入門者，店員都會主動介紹和推薦。\n\n**24小時宵夜社交：便利店和街頭小食**\n深夜1點以後，遊戲機中心陸續打烊，卡拉OK進入冷場時段。但旺角的夜生活並未結束，而是轉向便利店和街頭小食。7-11、OK便利店的桌位常坐滿年輕人，有人在購物同時進行小額消費，有人把便利店當作聊天室。周邊24小時營業的麻辣燙檔、大腸包小腸小食車，提供價格HK$15-35的快速填飽肚子選項。\n\n這種「便利店社交文化」在旺角特別濃厚。許多設計師、文案、自由工作者會在半夜來旺角便利店工作和社交，邊喝咖啡邊聊專案。這已成為一種非正式的「自由工作者夜間辦公室」文化，打造了一種獨特的24小時創意社交生態。\n\n**實用資訊**\n交通：旺角MTR站位於東湧線和荃灣線交匯處，從中環出發只需8分鐘。A1、A2出口分別靠近朗豪坊和新世紀廣場。\n營業時間：遊戲機中心通常營業至凌晨2-3點（部分24小時），卡拉OK至凌晨3-4點，便利店24小時。\n消費價格：遊戲機單輪HK$10-30，卡拉OK小店HK$60-120/小時，小食HK$15-35，飲品HK$20-40。\n最佳季節：全年都適合，冬季（11月-2月）人流相對較少，遊戲位置更容易搶到。\n\n**旅遊小提示**\n旺角街道複雜容易迷路，以朗豪坊或新世紀廣場作為地標導航更安全。週末人流龐大，遊戲機位置往往要排隊，工作日晚上7-10點相對清靜。許多小店卡拉OK和街頭小食檔只收現金，建議帶足現鈔。部分卡拉OK包廂可能設有年齡或身份驗證規定，事先詢問為佳。夜間治安良好，但人多雜亂，留意財物安全。對動漫和遊戲有興趣的旅客，建議下午先探店瞭解各店特色，晚上再來社交體驗。",
  "license": "CC BY 4.0"
}