{
  "title": "西貢夜生活：慢節奏巷弄中的深夜食堂與海濱夜色",
  "slug": "hongkong-entertainment-nightlife-sai-kung-西貢夜生活-慢節奏巷弄中的深夜食堂與海濱夜色-4868f6",
  "industry": "entertainment",
  "category": "nightlife",
  "area": "sai-kung",
  "url": "https://hongkong-encyclopedia.vercel.app/articles/hongkong-entertainment-nightlife-sai-kung-西貢夜生活-慢節奏巷弄中的深夜食堂與海濱夜色-4868f6.html",
  "published": "2026-06-01",
  "quality_score": 6.5,
  "word_count": 1054,
  "tags": [
    "西貢夜生活",
    "新界東夜遊",
    "香港深夜食堂",
    "海邊夜景",
    "本地人美食"
  ],
  "content": "很多人不知道，西貢的夜生活和新界的節奏一模一樣——慢。沒有銅鑼灣的喧囂啤酒波濤，沒有蘭桂坊的百萬卡座，這裡的晚上屬於那些願意花時間找店家的人。海風吹拂的碼頭邊，一盞盞昏黃燈光下藏著的，是香港最被低估的深夜味覺體驗。\n\n西貢舊墟路一帶是夜間覓食的核心戰區。和市區那種「開到凌晨三點但食物普通」的夜店不一樣，西貢晚上開店的餐廳不多，但每一家都有自己固定的客人。碼頭附近的海鮮大排檔傍晚開始營業，高峰期是晚上八點到十一點，主力客群是本地居民和少量懂得找路的遊客。推薦「洪記海鮮酒家」，人均消費大約200至400港元，價效比在新界東算是很不錯的選擇。老闆會推薦當天的特選海產，方法是看魚缸撈什麼——這也是識貨的人才知道的點菜技巧。\n\n如果想走更local的路線，西貢有幾間不掛招牌的糖水店，藏在普通住宅大樓的樓梯間。這些「野生糖水舖」沒有Instagram宣傳，沒有TripAdvisor評論，營業時間全看老闆心情。通常晚上十點才慢慢開門，賣完就關。楊枝甘露和腐竹糖水是基本盤，有些店家冬天會加推紅豆沙。價格大約25至45港元一碗，是那種「吃過下次還想再來」的隱藏版美味。\n\n西貢碼頭的夜景是免費的視覺享受。這裡不像維多利亞港有人山人海的旅客，只有三三兩兩的本地人坐在長椅上看船隻進出。如果你喜歡拍照提案，碼頭的盡頭是最推薦的位置，可以拍到鹵素燈光照映下的寧靜海面。這個畫面在市區找不到。\n\n稍微遠一點的萬宜水庫東壩是近年IG打卡的熱點，但實際上那裡晚上沒有路燈，安全係數偏低，適合日間健行而非夜晚活動。如果執意要看萬宜水庫的星空，需要自備手電筒並且組隊同行，避免單獨行動。\n\n西貢夜生活最大的價值不是「熱鬧」，而是你願意用多少時間去發現。在這個甚麼都要快的城市裡，能夠「慢慢搵、食慢慢」的夜體驗，其實比想象中更珍貴。下次如果你想逃離市區的啤酒噪音，西貢可能是香港唯一一個晚上可以真正安靜吃飯的地方。\n\n實用資訊方面，從港鐵彩虹站轉乘穿梭巴士到西貢大概需要三十分鐘，車資大約二十港元。或者從坑口站搭計程車，車程約十五分鐘，費用約七十至九十港元。西貢的餐廳普遍晚上十點後選擇減少，建議晚上七點到九點之間用餐是最理想的時間視窗。大部分海鮮餐廳接受現金和信用卡，但有些小路邊的糖水店只收現金،提醒各位旅客出發前準備足夠的港幣。\n\n旅遊小提示：千萬不要把西貢當作「墊檔」的行程安排,這裡是需要至少半天的目的地。晚上計程車離開西貢比較難截,建議提早預約電召服務或者計算好尾班車時間。夏天記得帶防蚊噴霧,碼頭附近的蚊蟲特別活躍。",
  "license": "CC BY 4.0"
}