{
  "title": "旺角潮流古著攻略：年輕人的復古 treasures獵場",
  "slug": "hongkong-shopping-antiques-mong-kok-旺角潮流古著攻略-年輕人的復古-treasures獵場-baed7a",
  "industry": "shopping",
  "category": "antiques",
  "area": "mong-kok",
  "url": "https://hongkong-encyclopedia.vercel.app/articles/hongkong-shopping-antiques-mong-kok-旺角潮流古著攻略-年輕人的復古-treasures獵場-baed7a.html",
  "published": "2026-06-03",
  "quality_score": 7.5,
  "word_count": 1968,
  "tags": [
    "旺角購物",
    "vintage",
    "古著",
    "香港潮流",
    "二手市集"
  ],
  "content": "說起旺角（Mong Kok），很多人第一印象是電子產品、廉價服飾和密集的人潮。如果你期待在這裡找到傳統紅木傢俱或明清瓷器，可能會失望。但正是這種「不符合預期」的特質，讓旺角成為香港少數能以合理價格接觸vintage文化的區域。\n\n旺角的定位向來不是傳統古董街。根據我對九龍各區古董店的觀察，租金成本差異直接影響了商品結構——港島古董店因為租金高昂，傾向經營高單價的精品；但九龍區，特別是旺角，能支撐更具活力的年輕化二手市場。這裡的「古董」定義應該放寬：我把它看作「有故事的舊物」，可能是八九十年代的香港製造球鞋、復古運動外套、本土設計師品牌存貨，或是有年代感的潮流小物。\n\n**旺角的獨特定位：年輕人的 vintage 獵場**\n\n旺角的vintage店舖集中度在全港算是難得的。不同於中上環那種需要鑑價知識的高單價古玩，旺角的二手店更親民——一件八成新的復古 Nike 球衣可能只需 HK$150-300，一條九十年代的 Levi's 牛仔褲大概 HK$400-800。這個價位帶，配合年輕人的消費能力，正是旺角的核心競爭力。\n\n值得一提的是，2026年初香港旅客量按年增長18%，其中不少是年輕的內地旅客，他們對「古著感」的追求，直接帶動了這類小店的人氣。如果你厭倦了連鎖品牌的同質化，旺角的巷弄裡確實藏著驚喜。\n\n**推薦店家：三家各有特色的旺角 vintage 寶藏**\n\n*1. Milk HK（男人的街一帶）*\nMilk HK 在旺角男人的街後段，主打八九十年代的日本潮流單品。老闆是資深「波鞋」愛好者，店記憶體貨以日本品牌為主，包括早期的 Undercover、Fragment Design 聯名款、日本製的 Nike 空軍外套等。這裡的價格約 HK$300-2,000，視年份和稀有程度而定。最大的優點是老闆會幫客人留意外海的 vintage 款式，熟客常有優先預訂權。店內禁止拍照，這規矩本身說明東西有一定價值。有趣的是，這類店主「靠眼光吃飯」的經營邏輯，和中上環那些家族經營的老古董店形成了鮮明對比——前者賣的是潮流觸覺，後者賣的是歷史知識。\n\n*2. The Little Room（女人街附近）*\n藏在女人街側巷的二樓，招牌很不明顯，但推開門之後完全是另一個世界。這家店主營香港八九十年代的本土設計品牌存貨，包括當年的利舞臺背後的原創服裝、香港製衣廠的外銷餘單。價格大約 HK$100-600，特別適合想找「香港製造」紀念品的旅客。一件1988年的香港製格子襯衫，做工紮實，圖案有那個年代的獨特審美，買回去送朋友或是自己穿都很有意思。老闆娘說，很多顧客是回頭客，有時候帶伴侶再來「尋寶」。這個業態在全港幾乎是獨一無二的——中上環的古董店不會賣這麼便宜的東西。\n\n*3. Retro Jam（朗豪坊對面）*\n朗豪坊對面的小店，主打美國七十八十年代的復古運動單品，包括 MLB 球衣、Vintage Tommy Hilfiger、Hang Ten 等當年的街頭品牌。店鋪很小，但貨篩選得認真。價格大約 HK$200-1,500，一件1990年代的正版 MLB 波士頓紅襪隊主場比賽球員版球衣，大約 HK$800 左右。這個價位在香港來說不算貴——同型別的單品在東京的 select shop 可能要貴上一倍。店主的選貨眼光確實不錯，至少我看到他進貨的時間點，都恰好是當下復古潮流的回溫週期。他自己的說法是：「不做網紅款，做經典款。」\n\n**實用資訊：交通、費用與營業時間**\n\n交通方面，搭乘 MTR 荃灣線或東鐵線到旺角站，B3 出口直通男人的街女人街一帶是最方便的。如果從羅湖或落馬洲口岸過關，直奔旺角建議乘東鐵線到九龍塘站，再轉一站就到旺角，總程約40分鐘。\n\n基本費用參考：\n- 一件普通 vintage T 恤：HK$150-400\n- 一條復古牛仔褲：HK$400-1,200\n- 經典球衣或外套：HK$600-2,000\n- 稀有款式或設計師聯名：價格面議，可能到 HK$3,000-5,000\n\n營業時間普遍在 中午12點至晚上9點，部分小店週一休息。建議安排下午傍晚時段，人潮相對較少，店主也有更多時間幫忙介紹貨品。\n\n**旅遊小提示**\n\n第一，下午三點過後是比較好的逛店時段，早上很多店還在理貨。第二，絕大多數店鋪可以講價，尤其是超過 HK$500 的單品，開口問一句通常有驚喜。第三，不要只看連鎖店林立的西洋菜街，拐進男人街和女人街的側巷，那些「二樓小店」往往更有驚喜。第四，記得帶現金——部分小店不收信用卡。最後，如果你真的在找「傳統意義上的古董」，建議改去中上環或是西貢，那邊的選擇更適合有明確收藏目標的客人，但在旺角，你一定能找到一些不一樣的東西——那種屬於年輕人自己的「舊物故事」。",
  "license": "CC BY 4.0"
}