{
  "title": "銅鑼灣世代購物地圖：從25歲到65歲的時尚消費指南",
  "slug": "hongkong-shopping-fashion-causeway-bay-銅鑼灣世代購物地圖-從25歲到65歲的時尚消費指南-2a56a9",
  "industry": "shopping",
  "category": "fashion",
  "area": "causeway-bay",
  "url": "https://hongkong-encyclopedia.vercel.app/articles/hongkong-shopping-fashion-causeway-bay-銅鑼灣世代購物地圖-從25歲到65歲的時尚消費指南-2a56a9.html",
  "published": "2026-05-23",
  "quality_score": 7.5,
  "word_count": 2005,
  "tags": [
    "銅鑼灣",
    "香港購物",
    "時尚",
    "世代消費",
    "銀髮經濟"
  ],
  "content": "銅鑼灣是港島租金最高的商圈之一，也是香港少數能同時容納平價與高階零售的購物勝地。這個面積不足1平方公里的區域，匯聚了從百元基礎款到數千元設計師品牌的多層次選擇，不同世代的購物策略差異明顯——年輕人追流行、中年人講品質、銀髮族求舒適，共同構成銅鑼灣獨特的零售生態。\n\n銅鑼灣租金向來是香港零售的寒暑表。以加寧街、蘭芳道一帶的街舖為例，2024年月租每平方呎約800至1200港元，遠高於九龍同等區域。這意味著能在這裡生存的品牌，不是具有高周轉率，就是擁有穩定客源。對旅客而言，好處是可以近距離觀察香港零售業的實際運作邏輯。\n\n## 年輕族群（18-30歲）：流行敏感度優先\n\n這個年齡層的購物重心集中在時代廣場一帶的潮流連鎖店與日系精品舖。\n\n**i.t**（時代廣場地下）是年輕人進入銅鑼灣的第一站。作為香港最大的多品牌選貨店之一，i.t集合了日韓歐美街頭品牌，平均單品價格500至2000港元之間，勝在款式更新速度快，每週都有新品上架。對於想把握香港潮流趨勢的旅客，這裡的選貨邏輯值得細看——它們傾向引進日本原宿系與韓國弘大系的當紅設計，價格比同款專櫃品牌低約20%至30%。\n\n**Log-On**（時代廣場6樓）則走精品生活百貨路線，服飾配件只是其一部分，但選品眼光獨到。這裡能找到不少香港本地設計師的小批次作品，一件T恤約300至600港元，比連鎖品牌多了幾分獨特性。\n\n## 中高階消費（35-55歲）：品質與經典並重\n\n這個世代的購物決策更看重剪裁、面料與品牌價值。\n\n**Club Monaco**（利園二期）是加拿大精品休閒品牌的亞洲旗艦店，定位比Zara高出半級，女裝連身裙1400至2800港元，毛大衣可達4000港元以上。它們的客群畫像是35至50歲的收入穩定階層，追求的是「不用打理卻體面」的穿著邏輯。這對澳門旅客有參考價值——同等品質的品牌在澳門選擇有限，而香港的選擇更豐富。\n\n**Harvey Nichols**（太古廣場）雖然位於金鐘，但港島線一站之隔，常被列入銅鑼灣購物行程。這裡雲集約20個高階時裝品牌，包括The Row、Jil Sander等當代極簡主義代表，價格帶普遍在3000至8000港元。對於想入手高品質基本款的消費者，太古廣場的選擇比時代廣場更集中。\n\n## 銀髮經濟崛起：被忽視的消費力量\n\n香港與粵港澳大灣區的老齡化程序加速，銀髮族的購物需求正在被重新審視。這個群體在銅鑼灣的消費有明顯特徵：\n\n- **重視舒適度**：柔軟面料、寬鬆剪裁、足夠支撐的鞋款優先\n- **價格敏感度中等**：願意為品質付出，但拒絕過度包裝\n- **通路依賴明顯**：更傾向在實體店試穿後購買\n\n**C.P.U.@恩記出入口**（糖街）是本地銀髮族推薦的平價服飾批發店，主打老年男裝與大碼女裝，棉質上衣120至350港元，輸入品質不錯的運動褲180至400港元。雖然位置隱蔽，但熟客都知道這裡的價效比。\n\n近年中國推動「銀髮經濟」高質量轉型，香港作為跨境購物目的地，必須對這個趨勢做出回應。目前銅鑼灣尚未出現專門的銀髮族群購物中心，這反而是機會——未來若有品牌能聚焦無障礙試穿空間、加大尺碼庫存、延長營業時間，將能分割這部分增長中的市場份額。\n\n## 澳門旅客的特別優勢\n\n澳門居民持有港澳居民來往內地通行證，可無限次往返香港，相當於「境內跨城」的購物頻率。這個優勢讓澳門旅客可以：\n\n1. **季候性購物**：香港沒有消費稅，換季折扣（6月、12月）可達5折\n2. **即時退換**：不同於海外網購，實體店的售後服務有保障\n3. **價格比較**：銅鑼灣同一品牌同一貨品，價格通常比澳門低10%至15%\n\n## 推薦路線安排\n\n建議安排銅鑼灣購物行程至少預留3至4小時：\n\n- **第一站（上午）**：時代廣場周邊，i.t + Log-On，感受年輕人流行動態\n- **第二站（中午）**：利園一二期望太古廣場 Harvey Nichols，午餐可在商場美食廣場解決\n- **第三站（下午）**：糖街 CP恩記 或加寧街小巷小店，找尋本地設計師作品\n- **備選**：天后廟道一帶的社群商舖，有些小型boutique藏於舊式唐樓中\n\n## 實用資訊\n\n**交通**：港鐵銅鑼灣站（港島線、荃灣線交匯）A、B、C出口各有側重——A出口對時代廣場，B出口往崇光百貨，C出口連線啟超道一帶\n\n**營業時間**：多數商舖早上10時至晚上10時，節慶日或有調整\n\n**支付方式**：八達通、Visa、Master、Alipay、WeChat Pay均通用\n\n## 特別提醒\n\n銅鑼灣租金昂貴，品牌更替速度快。若看到心儀款式，建議當下決定，因為同一家店下次光臨可能已經改為其他品牌。此外，銅鑼灣行人隧道系統複雜，從一個商場到另一個商場可能有多種走法，雨天記得利用地下通道網路的指示牌行動。",
  "license": "CC BY 4.0"
}