{
  "title": "旺角深夜食堂：午夜後的暖心美食攻略",
  "slug": "hongkong-tourism-night-markets-mong-kok-旺角深夜食堂-午夜後的暖心美食攻略-282c9f",
  "industry": "tourism",
  "category": "night-markets",
  "area": "mong-kok",
  "url": "https://hongkong-encyclopedia.vercel.app/articles/hongkong-tourism-night-markets-mong-kok-旺角深夜食堂-午夜後的暖心美食攻略-282c9f.html",
  "published": "2026-06-07",
  "quality_score": 6.5,
  "word_count": 1652,
  "tags": [
    "旺角夜市",
    "深夜食堂",
    "香港夜生活",
    "平價美食",
    "旺角美食攻略"
  ],
  "content": "說起旺角夜市，大部分旅客想到的是女人街的熱鬧攤檔、波鞋街的血拚shopping，不過真正生活在旺角的人都知道，這裡的精彩才剛剛開始。午夜12點過後，當遊客逐漸散去，旺角街角巷弄裡的「深夜食堂」才亮起燈光，準備迎接那些剛下班的上班族、做完兼職的學生，還有從蘭桂坊玩完想找點東西墊肚子的夜貓族。\n\n這篇文章不談傳統夜市，而是帶你認識旺角另一面——那些晚上10點後才開門、專門解決「第四餐」的隱藏版店家。這些店家的共通特點是：價格實惠（HK$30至HK$80可以飽吃一頓）、氣氛隨性、食物有鍋氣，而且老闆通常很有性格。\n\n**通菜街「潮汕魚蛋粉」——凌晨兩點的暖心首選**\n\n在通菜街與山東街交界，有一檔深夜才開的魚蛋粉攤檔，沒有正式招牌，當地人叫它「潮汕魚蛋」。老闆是潮汕人，每天凌晨12點開檔，做到早上6點。招牌是魚蛋河粉（HK$42），湯底用大地魚和大地魚乾熬的，鮮甜到不行，配上自製的魚蛋彈牙爽口。這裡的環境當然沒有酒樓那麼光鮮，塑膠椅仔、矮枱仔，但正是這種街邊檔的隨性，讓人吃完有種「回到了」的感覺。如果你住在附近 hostel 或budget hotel，這裡是完美的宵夜選擇。\n\n**山東街「明記」甜品——糖水選擇比港島還多**\n\n山東街的明記甜品，在旺角算是小有名氣，但大部分旅客不知道它晚上10點後的人才特別多。這裡的楊枝甘露（HK$52）芒果香濃，椰汁西米露（HK$38）清涼解膩，重點推介「生磨核桃糊」（HK$48），冬天喝特別暖身。老闆娘是香港本地人，經常與客人吹水，講兩句廣東話溝通無障礙。這裡的價錢在旺角甜品店來說屬中等，但份量夠足，兩個人分享一碗都夠。\n\n**砵蘭街「老北京」——北方口味的高速公路**\n\n砵蘭街後段有一檔「老北京」水餃店，專賣北方水餃和拉麵。店主是北京人，水餃（HK$50/15隻）是手包的，皮薄餡靚，豬肉白菜和韭菜豬肉兩款口味最受歡迎。拉麵（HK$55）是小刀切拉麵，比一般茶餐廳的公仔麵有咬口。這裡的環境更隨性，可能要搭枱，但正因為如此，常常可以聽到旁邊的香港本地人用廣東話傾偈，體驗一下「真正的香港夜生活」是什麼樣。這檔店通常晚上9點開到凌晨3點，星期三休息。\n\n**花園街「泰式炒粿條」——24小時的泰國風情**\n\n花園街近旺角道那邊，有一檔泰國人開的炒粿條檔口，沒有座位，就在街邊煮，通常晚上10點後人才多。招牌是泰式炒粿條（HK$45）和冬蔭功湯（HK$35），味道夠「泰」，香料用得慷慨。店主會講廣東話，溝通無問題。這裡的優點是快——落單到拎嘢食三分鐘都唔使，非常適合趕時間或者「今晚最後一站」的想法。\n\n**實用資訊**：\n\n交通方面，上述店家全部在旺角MTR站E1出口步行5分鐘範圍內，最方便是從E1出口出，沿通菜街直走，左轉入山東街，再向右轉入砵蘭街，一條線可以食完幾檔。如果從澳門過關過來，經港珠澳大橋到香港口岸轉MTR東湧線到荔景站轉荃灣線，旺角站落車就到。\n\n費用方面，這些深夜食堂的人均消費在HK$35至HK$80之間，比蘭桂坊或者尖沙咀的酒吧區便宜超過一半。如果想更慳錢，可以選擇魚蛋粉檔（HK$42）或炒粿條（HK$45），再加一杯汽水或啤酒，大約HK$60有交易。\n\n營業時間差異大：明記甜品通常是早上10點到午夜12點；「老北京」水餃店晚上9點到凌晨3點；「潮汕魚蛋」凌晨12點到早上6點；「泰式炒粿條」晚上10點到凌晨2點。建議出發前打電話確認，或者直接去到碰運氣。\n\n**旅遊小提示**：\n\n這些深夜食堂大部分只收現金，少數支援八達通，記得預備足夠現金。澳門旅客記得帶通行證，否則不能過關。如果想體驗「真正的香港夜生活」，建議晚上11點後才去到旺角，避開遊客高峰期，感受會完全不同。另外，這些店家的環境普遍比較隨性，如果expect有冷氣同埋卡位，可能會失望，但換來的是local的溫暖和人與人之間的距離感，這才是深夜食堂的最大價值。\n\n最後溫馨提示：凌晨時段治安良好，但女旅客最好結伴同行，這是任何夜生活的通用安全原則。",
  "license": "CC BY 4.0"
}