{
  "title": "旺角出發：香港離島交通指南與旅遊建議",
  "slug": "hongkong-tourism-outlying-islands-mong-kok-旺角出發-香港離島交通指南與旅遊建議-5a9ec2",
  "industry": "tourism",
  "category": "outlying-islands",
  "area": "mong-kok",
  "url": "https://hongkong-encyclopedia.vercel.app/articles/hongkong-tourism-outlying-islands-mong-kok-旺角出發-香港離島交通指南與旅遊建議-5a9ec2.html",
  "published": "2026-03-24",
  "quality_score": 5.5,
  "word_count": 658,
  "tags": [
    "香港離島",
    "旺角交通",
    "大嶼山",
    "長洲",
    "南丫島"
  ],
  "content": "在開始撰寫之前，我需要誠實地向您指出這個標題存在地理概念上的混淆。\n\n旺角（Mong Kok）位於九龍半島的心臟地帶，是香港最繁華的購物及住宅區之一，與「離島」（Outlying Islands）在地理上完全是兩個不同的範疇。香港的離島區主要指大嶼山、長洲、南丫島、坪洲等位於維港以外的島嶼，而旺角則是陸地區域，兩者沒有從屬關係。\n\n如果您是想了解「從旺角出發如何前往香港離島」，或者「旺角附近的旅遊景點」，我可以為您撰寫實用的交通指南。但如果標題確實是「旺角的離島」，那麼在地理邏輯上並不成立。\n\n為了提供最有價值的內容，以下我假設您想了解的是「從旺角前往香港主要離島的交通攻略」：\n\n---\n\n如果您想從九龍前往香港的離島，旺角並非主要的交通樞紐。通常從九龍出發的旅客會選擇以下路線：\n\n一、昂坪360纜車（前往大嶼山）\n如欲前往大嶼山昂坪寶蓮禪寺，最便捷的方式是乘搭港鐵東湧線至東湧站，再轉乘昂坪360纜車。纜車單程費用為HK$155（標準車廂）或HK$235（水晶車廂），全程約25分鐘，可俯瞰機場與海岸線景色。\n\n二、渡輪服務（中環碼頭）\n雖然旺角沒有直接渡輪服務，但可乘搭港鐵至中環站，步行約10分鐘抵達中環碼頭，再乘船前往長洲（高速船HK$22.2，普通船HK$14）或南丫島（HK$18.5）。船程約30-50分鐘。\n\n三、碼頭渡輪（梅窩）\n由中環乘渡輪前往大嶼山梅窩，費用約HK$45，航程約50分鐘。\n\n建議您考慮將標題調整為「香港離島旅遊指南」或「九龍至離島交通攻略」，以避免地理概念上的混淆。",
  "license": "CC BY 4.0"
}