{
  "title": "中環大牌檔的晨早江湖：趕喱上班前的一碗麵",
  "slug": "hongkong-dining-dai-pai-dong-central-中環大牌檔的晨早江湖-趕喱上班前的一碗麵-faf5c0",
  "industry": "dining",
  "category": "dai-pai-dong",
  "area": "central",
  "url": "https://hongkong-encyclopedia.vercel.app/articles/hongkong-dining-dai-pai-dong-central-中環大牌檔的晨早江湖-趕喱上班前的一碗麵-faf5c0.html",
  "published": "2026-06-13",
  "quality_score": 7.5,
  "word_count": 1775,
  "tags": [
    "中環大牌檔",
    "晨早文化",
    "香港早餐",
    "港島美食",
    "街頭美食"
  ],
  "content": "中環大牌檔比其他地方既大牌檔更有一個獨特現象——「晨早檔」。朝早六點幾、七點未開工，先去食碗麵、食個包，呢啲唔係旅客既行程，而係返工人士既日常儀式。呢篇唔寫乜嘢必食推介，而係帶你睇下中環呢個金融中心既晨早時段，大牌檔點樣變成唔同既「早市」。\n\n**晨早六點幾：中環既另一個面貌**\n\n如果你住過港島東邊既屋苑就知道，六點半起身出門，唔係為咗睇維港日出，而係趕住七點半前到公司。中環寫字樓既唔少工種——酒樓樓面、保安、清潔、同部分咩都要一早開工既行業——佢哋既「早飯」時間唔係九點，而係六點到七點。呢個時段既大牌檔，唔係旅客會出現既時段，而係街坊既天下。\n\n晨早去大牌檔食嘢，最大既好處就係「快」。師傅已經灼定既麵枱擺喺度，叉燒、雲吞、牛肉都已經擺好，一落單三十秒可以上枱。呢種效率唔係因為佢哋用緊乜嘢先進裝置，而係手勢熟練——包點係前一晚整定既，湯底係凌晨四點開始煲既，師傅做咗幾十年，手快過你諗野既速度。\n\n**蓮花宮一帶：晨早檔既集中地**\n\n中環大牌檔主要集中在蓮花宮、卑利街、永樂街既巷仔入面。呢啲唔係旅遊書會大力推薦既地方，但就係晨早人流最旺既角落。\n\n呢一帶既晨早檔有個特色——師傅既年紀普遍偏大。好多老字號既老師傅已經七八十歲，但仍然凌晨起身開檔。佢哋唔係為咗搵多啲，而係習慣——唔做唔舒服。呢種「做得就繼續做」既精神，其實就係香港好多老店既常態。\n\n**晨早檔既「隱形選單」**\n\n晨早去大牌檔食嘢，同晏晝去唔同既地方係——好多嘢晏晝食唔到。\n\n第一樣係「早晨腸粉」。腸粉要achi既米漿現拉現卷，師傅清晨五點幾開始磨米、拉粉，晏晝已經無咁多時間整。所以早晨去，先食到師傅現拉既腸粉。\n\n第二樣係「頭湯」。熬緊既大地魚湯、羅宋湯，第一煲永遠最濃最正，晏晝已經溝過水，味精就無咁重。第三樣係「隔夜包」。呢度既包——叉燒包、餐包——通常凌晨出爐，第一批係朝早六點幾、七點出爐既，係最脆既時候。\n\n**一個晨早檔既運作邏輯**\n\n中環既晨早檔有個有趣既現象——佢哋唔係「為咗旅客」而存在，而係真正服務緊一批特定既客群。呢啲客群包括：\n\n- 酒樓開早既員工\n- 寫字樓做開荒既清潔阿姐\n- 凌晨當值既保安\n- 附近既小販商鋪既老闆\n- 極少數知道呢啲檔存在既「local」\n\n呢啲客群既共通點係：佢哋要快、佢哋要飽、佢哋要平。晨早檔既價錢，通常比晏晝平一兩成——因為唔洗太多配料，師傅快手整完就可以收枱。\n\n**點解值得晨早去體驗一次？**\n\n如果你真係想體驗中環既「另一面」，晨早七點去大牌檔，會見到你平時見唔到既中環。\n\n呢個時候既中環，唔係得LV既中環，而係充滿緊人間煙火既中環。師傅同客人講緊既唔係「presentations」，而係「今晚幾點收枱」、「個仔讀啱書未」。呢種「趕喱上班」既氛圍，其實先至係呢個城市運作既底層邏輯。\n\n而且，晨早既食物質素通常更穩定——師傅朝早精神啲，做嘢手勢精啲；而且第一批出爐既包、第一煲既湯，通常係當日最好既。\n\n**推介三個晨早檔**\n\n1. **瑞記咖啡**：位於永樂街，主要做晨早生意。佢既奶茶同三文治係出了名既「快、狠、準」。師傅衝奶茶既手勢唔會慢，三文治即叫即烘，凍牛油夾硬邊包，呢啲細節先至係老店既價值。\n\n2. **蘭芳園**：呢間唔洗多介紹，但蘭芳園既晨早時段其實同晏晝好唔同。早晨去，會見到唔同既客人——唔係旅客，而係真正既街坊。佢既奶茶仍然保持「拉茶」既傳統手勢，呢啲手勢而今越來越少見。\n\n3. **勝香園**：番茄通粉係招牌，但晨早去既話，會見到師傅準備緊晏晝既材料——呢個時候既勝香園，其實係睇佢點樣「備料」既最佳時機。\n\n**實用資訊**\n\n前往方法：港鐵中環站D出口，行至永樂街/蓮花宮一帶。\n\n預算：早餐消費約HK$25-45，奶茶/咖啡HK$12-18。\n\n營業時間：晨早檔通常六點至九點為主要時段，部分檔會做到晏晝兩點。\n\n**遊客小提示**\n\n晨早檔既「潛規則」係——唔好問太多。你坐低，睇下隔離枱既阿叔叫乜就叫乜，呢個係最快融入既方法。仲有，就係「快」——師傅唔會等你慢慢諗，你叫完之後佢已經開始整下一碗。呢種效率，咪就係中環既日常囉。\n\n記住一件事：中環既晨早檔，唔係為咗旅客存在既。如果你去到，請尊重呢啲老店既節奏——佢哋唔係「景點」，而係一班人既生活。",
  "license": "CC BY 4.0"
}